{
   "POST" : 
      {
         "BizPhone" : 4265,
         "Notes" : "Owner Operator",
         "AuthorityLevel" : "executive",
         "biz_phone" : {
            "Number" : "916-389-4508",
            "PhnFaxId" : 4265,
            "Mobility" : "LAND LINE",
            "Features" : "VOICE",
            "Extension" : "0",
            "Notes" : null
         },
         "CurrentTitle" : "Owner",
         "AstId" : 15,
         "NodeId" : 399,
         "DateCreated" : "2019-12-10 10:30:24",
         "BizFax" : 4257,
         "biz_fax" : {
            "PhnFaxId" : 4257,
            "Number" : "916-515-8066",
            "Mobility" : "LAND LINE",
            "Extension" : "0",
            "Features" : "VOICE",
            "Notes" : null
         },
         "PrimaryContact" : 0,
         "node" : {
            "UnitName" : "Executive Office",
            "NodeId" : 399,
            "ParentId" : null,
            "Type" : "Other"
         },
         "ast" : {
            "FirstName" : "TestDriver",
            "BrnchId" : 3805,
            "LastName" : "DriverTest",
            "MiddleName" : "",
            "Suffix" : "",
            "Prefix" : "",
            "NickName" : ""
         },
         "BizEmail" : "hello@123.com",
         "DateRemoved" : null
      }
}
